README.md
setup.cfg
setup.py
cgivar2gvcf/__init__.py
cgivar2gvcf/__main__.py
cgivar2gvcf.egg-info/PKG-INFO
cgivar2gvcf.egg-info/SOURCES.txt
cgivar2gvcf.egg-info/dependency_links.txt
cgivar2gvcf.egg-info/requires.txt
cgivar2gvcf.egg-info/top_level.txt