Metadata-Version: 1.1
Name: cgivar2gvcf
Version: 0.1.8
Summary: Conversion of Complete Genomics var file to gVCF
Home-page: https://github.com/madprime/cgivar2gvcf
Author: Mad Price Ball
Author-email: mpball@gmail.com
License: MIT
Platform: UNKNOWN
Classifier: Development Status :: 2 - Pre-Alpha
